{
  "site": "The Pearson Co.",
  "repo": "Pearson26/pearson-co",
  "next_index": 431,
  "posts_published": 117,
  "total_planned": 1085,
  "last_published_slug": "procure-to-pay-process",
  "last_updated": "2026-07-22T23:13:38Z",
  "notes": "117 posts live. This run (2026-07-22): seq 428-430, three authority posts across three pillars, all site/blog/. 'What is customer journey mapping?' (Customer Journey Mapping, definition, global; McKinsey's Winter 2016 Customer Experience research cited, 10-15% revenue growth and 15-20% lower cost to serve from journey-based transformation; distinct angle from the existing what-is-a-customer-journey-map.html by covering the research-and-workshop process rather than the map artefact, kept overlap low; five-step process, worked example of a 25-person SaaS company's onboarding-journey fix; up-link spec's 'customer-journey-mapping-service' money page is not live and no other money page exists yet in this pillar, so linked only to the live pillar customer-journey-mapping.html per the Connector's 'link only to what is live' rule; lateral to what-is-a-customer-journey-map.html and mapping-the-buyer-journey.html). 'A market entry strategy framework' (Hospitality Tech & Middle East Expansion, guide, global; Lodging Econometrics Q4 2025 Middle East hotel construction pipeline cited, 710 projects/176,402 rooms record high, Saudi Arabia 394 projects/106,521 rooms up 25% YoY, UAE 104 projects/25,459 rooms; six-stage framework plus an entity-structure comparison table and a nine-month worked example of a UK hotel tech firm's Dubai entry; links to hospitality-tech-market-entry.html (pillar) and market-entry-strategy-service.html (money), both live and exactly as specified; lateral to types-of-market-entry-strategies.html and hospitality-technology-companies.html). 'The procure-to-pay process' (Process Mapping & SOP Creation, guide, global; Ardent Partners' Accounts Payable Metrics that Matter in 2025 report cited, 212 AP professionals surveyed, $12.88 average manual invoice cost vs under $2.78 best-in-class, 17.4 days vs 3.1 days processing time, 22% vs 9% exception rate; six-step P2P cycle plus a manual-vs-automated comparison table, HowTo schema added, worked example of a 60-person hospitality group's rollout; up-link spec's 'process-mapping-service' money page is not live and no other money page exists yet in this pillar, so linked only to the live pillar process-mapping.html; lateral to process-map-symbols.html and business-process-automation.html). All three passed style gate on first run: 0 em dashes, 0 banned words, British spelling throughout, checked via style_gate.py across the full site/blog/ and site/services/ tree (clean). Word counts clear of type floors: what-is-customer-journey-mapping 1,115 words (definition floor 900), market-entry-strategy-framework 1,525 words (guide floor 1,500), procure-to-pay-process 1,513 words (guide floor 1,500). Article+FAQPage+BreadcrumbList schema valid on all three, plus HowTo on the procure-to-pay post; 5 FAQs each, exactly one H1 each, all internal link targets confirmed live on disk before commit. All three new posts were initially unlinked from elsewhere in the graph; fixed proactively before running link_graph.py by adding an inbound Related-reading link from the two sibling pages each links out to (what-is-a-customer-journey-map.html + mapping-the-buyer-journey.html; types-of-market-entry-strategies.html + hospitality-technology-companies.html; process-map-symbols.html + business-process-automation.html). link_graph.py reports the full graph clean (117 pages, 0 issues) with zero orphans on this run. Blog index regenerated (78 posts, 14 pillars). Sitemap updated (121 URLs). Dates on each article: 22 July 2026 / 2026-07-22, matching the actual run date, in both the visible byline and the JSON-LD datePublished/dateModified. Per the standing client note that articles 'are all published as June 16th': this was investigated and closed out as a non-issue in the 2026-07-21 run (the only pages genuinely dated 16 June 2026 are the original seq 1-39 pillar/money launch batch, confirmed against git first-commit dates, and that date is factually correct for those evergreen pages, not a bug). The per-run dating mechanism itself has no live bug and continues to date every new post to its actual publish day; no further action needed unless a specific new page is found misdated. Slack link format: continuing the standard-Markdown `[Title](url)` convention adopted in the 2026-07-21 run (one article per line, no native Slack mrkdwn `<url|text>` syntax) since the slack_send_message tool renders standard Markdown, not Slack mrkdwn; this should keep links from bleeding into adjacent text. Pending money pages: customer-journey-mapping-service, customer-journey-mapping-workshop, customer-journey-mapping-consultant, customer-experience-consulting (customer-journey pillar, none live yet); process-mapping-service, sop-creation-service, sop-consultant, process-improvement-consulting, restaurant-sop-service, sop-template-pack, process-documentation-service, hospitality-sop-service, process-optimisation-consulting, workflow-automation-service, business-process-management-consulting, operations-manual-service, lean-process-consulting (process-sop pillar, none live yet), plus the previously noted backlog (sales-dashboard-service, crm-consultant-service, crm-adoption-consulting, positioning-and-messaging-service, dynamics-crm-implementation, salesforce-consultant, crm-automation-service, sales-analytics-consulting, crm-consultant-for-startups, crm-training-service, zoho-crm-implementation, customer-journey-mapping-service, hospitality-tech-consultant, go-to-market-strategy-consulting, product-launch-consulting, b2b-gtm-strategy-service, saas-gtm-strategy-service, gtm-strategy-uae). Note: verify_state.py resets next_index to the first sequential gap (seq 40) on every --write; next_index here is the Strategist intent pointer, manually set after each --write to (highest published seq + 1). Routine resumes at next_index=431."
}